pyinferno-0.2.6.dist-info/METADATA
pyinferno-0.2.6.dist-info/WHEEL
pyinferno-0.2.6.dist-info/entry_points.txt
pyinferno-0.2.6.dist-info/license_files/LICENSE.md
pyinferno/cli.py
pyinferno/profiler.py
pyinferno/py.typed
pyinferno/pyinferno.pyi
pyinferno/renderer.py
pyinferno/__init__.py
pyinferno/pyinferno.cp39-win_amd64.pyd
pyinferno-0.2.6.dist-info/RECORD
