Metadata-Version: 2.1
Name: pyinferno
Version: 0.2.6
Classifier: Programming Language :: Rust
Classifier: Programming Language :: Python :: Implementation :: CPython
Requires-Dist: pyinstrument
License-File: LICENSE.md
Summary: Simple python flame graph generator
Requires-Python: >=3.7
